evtx2df/README.md
evtx2df/__init__.py
evtx2df/requirements.txt
evtx2df/thirdparty.json
evtx2df-0.10.dist-info/LICENSE.rst
evtx2df-0.10.dist-info/METADATA
evtx2df-0.10.dist-info/WHEEL
evtx2df-0.10.dist-info/top_level.txt
evtx2df-0.10.dist-info/RECORD
