Metadata-Version: 2.1
Name: evtx2df
Version: 0.10
Summary: converts Windows Event Logs (EVTX) into pandas DataFrames / CSV files
Home-page: https://github.com/hansalemaos/evtx2df
Author: Johannes Fischer
Author-email: aulasparticularesdealemaosp@gmail.com
License: MIT
Keywords: EVTX,csv,convert,pandas
Classifier: Development Status :: 4 - Beta
Classifier: Programming Language :: Python :: 3 :: Only
Classifier: Programming Language :: Python :: 3.10
Classifier: Topic :: Software Development :: Libraries :: Python Modules
Classifier: Topic :: Utilities
License-File: LICENSE.rst
Requires-Dist: a-pandas-ex-apply-ignore-exceptions
Requires-Dist: a-pandas-ex-horizontal-explode
Requires-Dist: Evtx
Requires-Dist: flatten-any-dict-iterable-or-whatsoever
Requires-Dist: getfilenuitkapython
Requires-Dist: pandas
Requires-Dist: python-evtx
Requires-Dist: touchtouch
Requires-Dist: uffspd
Requires-Dist: ujson
